LICENSE
README.md
setup.py
savprogram/__init__.py
savprogram/asearch.py
savprogram/bruteforce.py
savprogram/hillclimbing.py
savprogram/simulatedannealing.py
savprogram/utils.py
savprogram.egg-info/PKG-INFO
savprogram.egg-info/SOURCES.txt
savprogram.egg-info/dependency_links.txt
savprogram.egg-info/top_level.txt