Metadata-Version: 2.2
Name: savprogram
Version: 0.0.1
Summary: A library with different Machine Learning Algorithms: Hill Climbing, Simulated Annealing, Brute Force, and A star search
Home-page: 
Author: Savannah Shannon
Author-email: snshannon2002@gmail.com
Keywords: ai algorithms
Classifier: Intended Audience :: Education
Classifier: Operating System :: Microsoft :: Windows :: Windows 11
Classifier: License :: OSI Approved :: GNU General Public License v3 (GPLv3)
Classifier: Programming Language :: Python :: 3.11
License-File: LICENSE
Dynamic: author
Dynamic: author-email
Dynamic: classifier
Dynamic: description
Dynamic: keywords
Dynamic: summary
